PostgreSQLDB.py
robotframework_postgresqldb-2.0.0.dist-info/LICENSE
robotframework_postgresqldb-2.0.0.dist-info/METADATA
robotframework_postgresqldb-2.0.0.dist-info/WHEEL
robotframework_postgresqldb-2.0.0.dist-info/top_level.txt
robotframework_postgresqldb-2.0.0.dist-info/RECORD
