Metadata-Version: 2.1
Name: robotframework-postgresqldb
Version: 2.0.0
Summary: Robot Framework Library For Working With PostgreSQL Database.
Home-page: https://github.com/peterservice-rnd/robotframework-postgresqldb
Author: Nexign
Author-email: mf_aist_all@nexign-systems.com
License: Apache License 2.0
Keywords: testing testautomation robotframework autotest psycopg2 postgresql database
Platform: UNKNOWN
Classifier: Development Status :: 5 - Production/Stable
Classifier: Intended Audience :: Developers
Classifier: Topic :: Software Development :: Testing
Classifier: License :: OSI Approved :: Apache Software License
Classifier: Programming Language :: Python :: 3.5
Classifier: Programming Language :: Python :: 3.6
Classifier: Framework :: Robot Framework :: Library
Requires-Dist: robotframework
Requires-Dist: psycopg2
Requires-Dist: future (>=0.16.0) ; python_version<="2.7"
